circleci_api_python/__init__.py
circleci_api_python/client.py
circleci_api_python/exceptions.py
circleci_api_python/resources.py
circleci_api_python/utils/__init__.py
tests/test_api_checkout_key.py
tests/test_api_context.py
tests/test_api_job.py
tests/test_api_orb_level_claims.py
tests/test_api_pipeline.py
tests/test_api_project.py
tests/test_api_user.py
tests/test_api_webhook.py
tests/test_api_workflow.py
tests/test_circleci_class.py
circleci_api_python-0.0.2.dist-info/LICENSE
circleci_api_python-0.0.2.dist-info/METADATA
circleci_api_python-0.0.2.dist-info/WHEEL
circleci_api_python-0.0.2.dist-info/top_level.txt
circleci_api_python-0.0.2.dist-info/RECORD
