Metadata-Version: 2.2
Name: circleci-api-python
Version: 0.0.2
Summary: Python API for CircleCI
Home-page: https://github.com/rkitsylinskyy/circleci-api-python
Author: Rostyslav Kitsylinskyy
Author-email: Rostyslav Kitsylinskyy <rostyslav.kitsylinskyy@gmail.com>
License: MIT License
Project-URL: author-homepage, https://www.linkedin.com/in/rostyslav-kitsylinskyy-587108118/
Project-URL: repository, https://github.com/rkitsylinskyy/circleci-api-python
Keywords: circleci,api,python
Classifier: Intended Audience :: Developers
Classifier: License :: OSI Approved :: MIT License
Classifier: Programming Language :: Python :: 3
Classifier: Programming Language :: Python :: 3.8
Classifier: Programming Language :: Python :: 3.9
Classifier: Programming Language :: Python :: 3.10
Classifier: Programming Language :: Python :: 3.11
Classifier: Programming Language :: Python :: 3 :: Only
Classifier: Programming Language :: Python :: Implementation :: CPython
Classifier: Programming Language :: Python :: Implementation :: PyPy
Classifier: Topic :: Software Development :: Libraries
Classifier: Topic :: Software Development :: Libraries :: Python Modules
Classifier: Typing :: Typed
Requires-Python: >=3.8
License-File: LICENSE
Requires-Dist: requests
Requires-Dist: setuptools
Provides-Extra: dev
Requires-Dist: pip-tools; extra == "dev"
Requires-Dist: pytest; extra == "dev"
Requires-Dist: pylint; extra == "dev"
Dynamic: author
Dynamic: home-page
Dynamic: requires-python
